usts/__init__.py
usts/__main__.py
usts/cfg.py
usts/mkmod-test.py
usts/mkmod.py
usts/module.py
usts/usts.py
usts/utils.py
usts/modules/modbat.py
usts/modules/modcpu.py
usts/modules/moddisk.py
usts/modules/modram.py
usts/modules/modstr.py
usts/modules/modtemp.py
usts/modules/modtime.py
usts/modules/modweather.py
usts/modules/modxkbstate.py
usts-0.1.81.dist-info/LICENSE
usts-0.1.81.dist-info/METADATA
usts-0.1.81.dist-info/WHEEL
usts-0.1.81.dist-info/entry_points.txt
usts-0.1.81.dist-info/top_level.txt
usts-0.1.81.dist-info/RECORD
