Metadata-Version: 2.1
Name: usts
Version: 0.1.81
Summary: Simple cli tool for creating status text to something like dwm-bar.
Home-page: https://notabug.org/loliconshik3/usts
Author: loliconshik3
License-File: LICENSE
